gage/__init__.py
gage/__main__.py
gage/gagefile.schema.json
gage/summary.schema.json
gage/userconfig.schema.json
gage/_internal/__init__.py
gage/_internal/ansi_util.py
gage/_internal/api.py
gage/_internal/attr_log.py
gage/_internal/board_util.py
gage/_internal/channel.py
gage/_internal/cli.py
gage/_internal/exitcodes.py
gage/_internal/file_select.py
gage/_internal/file_util.py
gage/_internal/gagefile.py
gage/_internal/lang.py
gage/_internal/log.py
gage/_internal/opref_util.py
gage/_internal/progress_util.py
gage/_internal/project_util.py
gage/_internal/python_util.py
gage/_internal/repo.py
gage/_internal/repo_git.py
gage/_internal/repo_local.py
gage/_internal/repo_rclone.py
gage/_internal/repo_util.py
gage/_internal/run_comment.py
gage/_internal/run_config.py
gage/_internal/run_config_py.py
gage/_internal/run_context.py
gage/_internal/run_dependencies.py
gage/_internal/run_filter.py
gage/_internal/run_help.py
gage/_internal/run_output.py
gage/_internal/run_select.py
gage/_internal/run_sourcecode.py
gage/_internal/run_util.py
gage/_internal/schema_util.py
gage/_internal/shlex_util.py
gage/_internal/sys_config.py
gage/_internal/test.py
gage/_internal/typer_rich_util.py
gage/_internal/types.py
gage/_internal/user_config.py
gage/_internal/util.py
gage/_internal/var.py
gage/_internal/vcs_util.py
gage/_internal/yaml_util.py
gage/_internal/commands/associate.py
gage/_internal/commands/associate_impl.py
gage/_internal/commands/board.py
gage/_internal/commands/board_impl.py
gage/_internal/commands/cat.py
gage/_internal/commands/check.py
gage/_internal/commands/check_impl.py
gage/_internal/commands/comment.py
gage/_internal/commands/comment_impl.py
gage/_internal/commands/copy.py
gage/_internal/commands/copy_impl.py
gage/_internal/commands/delete.py
gage/_internal/commands/delete_impl.py
gage/_internal/commands/error_handlers.py
gage/_internal/commands/help.py
gage/_internal/commands/impl_support.py
gage/_internal/commands/label.py
gage/_internal/commands/label_impl.py
gage-0.1.2.dist-info/AUTHORS.md
gage-0.1.2.dist-info/LICENSE.txt
gage-0.1.2.dist-info/METADATA
gage-0.1.2.dist-info/WHEEL
gage-0.1.2.dist-info/entry_points.txt
gage-0.1.2.dist-info/top_level.txt
gage-0.1.2.dist-info/RECORD
