Metadata-Version: 2.1
Name: gage
Version: 0.1.2
Summary: Model evaluation and publishing toolkit
Author-email: Garrett Smith <garrett@placeon.earth>
Project-URL: Homepage, https://github.com/gageml/gage
Project-URL: Bug Tracker, https://github.com/gageml/gage/issues
Classifier: Programming Language :: Python :: 3
Classifier: License :: OSI Approved :: Apache Software License
Classifier: Operating System :: OS Independent
Requires-Python: >=3.10
License-File: LICENSE.txt
License-File: AUTHORS.md
Requires-Dist: click >=8.1.7
Requires-Dist: chardet >=5.2.0
Requires-Dist: human-readable >=1.3.4
Requires-Dist: jschon >=0.11.1
Requires-Dist: lark >=1.1.9
Requires-Dist: libcst >=1.3.1
Requires-Dist: natsort >=8.4.0
Requires-Dist: proquint >=0.2.1
Requires-Dist: psutil >=5.9.8
Requires-Dist: python-ulid >=2.4.0
Requires-Dist: pyyaml >=6.0.1
Requires-Dist: requests >=2.31.0
Requires-Dist: rich >=13.7.1
Requires-Dist: setuptools >=69.2.0
Requires-Dist: tomli >=2.0.1
Requires-Dist: typer >=0.12.3
Provides-Extra: dev
Requires-Dist: black ; extra == 'dev'
Requires-Dist: groktest ; extra == 'dev'
